HTMLPackImagesaver/HTMLPackImagesaver.py
HTMLPackImagesaver/__init__.py
HTMLPackImagesaver/__main__.py
HTMLPackImagesaver-1.0.2.dist-info/LICENSE
HTMLPackImagesaver-1.0.2.dist-info/METADATA
HTMLPackImagesaver-1.0.2.dist-info/WHEEL
HTMLPackImagesaver-1.0.2.dist-info/top_level.txt
HTMLPackImagesaver-1.0.2.dist-info/RECORD
