Metadata-Version: 2.1
Name: HTMLPackImagesaver
Version: 1.0.2
Summary: Download and save images of HTML only archives - e.g. backup package of Medium.com
Home-page: https://github.com/otapi/HTMLPackImagesaver
Author: otapi
License: UNKNOWN
Platform: UNKNOWN
Classifier: Programming Language :: Python :: 3
Classifier: License :: OSI Approved :: Apache Software License
Classifier: Operating System :: OS Independent
Requires-Python: >=3
Requires-Dist: beautifulsoup4
Requires-Dist: requests
